{
    "id": 1191,
    "wordhead": "遱",
    "explanation": "連遱也。从辵婁聲。",
    "volume": "02",
    "radical": "辵",
    "pronunciation": "洛侯切",
    "variants": [],
    "seal_character": "匵",
    "pinyin": "lou",
    "pinyin_full": "lóu",
    "components": [
        "婁",
        "辵"
    ],
    "xuan_note": "",
    "kai_note": "",
    "duan_notes": [
        {
            "explanation": "連遱也。",
            "note": "連遱雙聲。集韵。連遱謂不絕皃。"
        },
        {
            "explanation": "从辵。婁聲。",
            "note": "洛侯切。四部。"
        }
    ],
    "indexes": [
        "遱"
    ]
}