{
    "id": 1380,
    "wordhead": "跇",
    "explanation": "述也。从足丗聲。",
    "volume": "02",
    "radical": "足",
    "pronunciation": "丑例切",
    "variants": [],
    "seal_character": "各",
    "pinyin": "yi",
    "pinyin_full": "yì",
    "components": [
        "足",
        "世"
    ],
    "xuan_note": "",
    "kai_note": "",
    "duan_notes": [
        {
            "explanation": "述也。",
            "note": "述當作𨒋。字之誤也。樂書。騁容與兮跇萬里。裴引如淳曰。？謂超逾也。吳都賦說田獵曰。？踰竹柏。？猭杞柟。"
        },
        {
            "explanation": "从足。世聲。",
            "note": "丑例切。十五部。鄒誕生云。跇一作世。"
        }
    ],
    "indexes": [
        "跇"
    ]
}