{
    "id": 1555,
    "wordhead": "諓",
    "explanation": "善言也。从言戔聲。一曰謔也。",
    "volume": "03",
    "radical": "言",
    "pronunciation": "慈衍切",
    "variants": [],
    "seal_character": "哊",
    "pinyin": "jian",
    "pinyin_full": "jiàn",
    "components": [
        "言",
        "戔"
    ],
    "xuan_note": "",
    "kai_note": "",
    "duan_notes": [
        {
            "explanation": "善言也。",
            "note": "善上當有諓諓二字。古文秦誓𢧵𢧵善諞言。諞字下引之。今文秦誓戔戔。戈部戔字下引之。釋云。巧言也。戔戔公羊傳作諓諓。云惟諓諓善靖言。劉向九歎、漢書李尋傳亦皆作諓諓。王逸注楚辭。引尚書諓諓靖言。正皆今文尚書也。諸家作諓許作戔者、同一今文而有異本。如同一古文而馬作偏許作諞不同也。戔下旣引戔戔矣。而諓下又云善言者。此又用王逸所據諓諓靖言之本也。善言釋靖言。何休曰。靖猶撰也。撰同譔。譔言、善言也。廣雅釋訓曰。諓諓、善也。賈逵外傳注曰。諓諓、巧言也。韋昭注曰。諓諓、巧辨之言。然則此善言、謂善爲言辭者。不同䛡下之善言也。"
        },
        {
            "explanation": "从言。戔聲。",
            "note": "慈衍切。十四部。"
        },
        {
            "explanation": "一曰謔也。",
            "note": "别一義。"
        }
    ],
    "indexes": [
        "諓"
    ]
}