{
    "id": 1572,
    "wordhead": "謼",
    "explanation": "𧦝謼也。从言虖聲。",
    "volume": "03",
    "radical": "言",
    "pronunciation": "荒故切",
    "variants": [],
    "seal_character": "哜",
    "pinyin": "hu",
    "pinyin_full": "hū",
    "components": [
        "言",
        "虖"
    ],
    "xuan_note": "",
    "kai_note": "",
    "duan_notes": [
        {
            "explanation": "𧦝也。",
            "note": "依韵會訂。此與口部嘑異義而通用。大雅崔本。式號式謼。"
        },
        {
            "explanation": "从言。虖聲。",
            "note": "荒故切。五部。"
        }
    ],
    "indexes": [
        "謼"
    ]
}