{
    "id": 1621,
    "wordhead": "謧",
    "explanation": "謧詍，多言也。从言离聲。",
    "volume": "03",
    "radical": "言",
    "pronunciation": "呂之切",
    "variants": [],
    "seal_character": "唓",
    "pinyin": "li",
    "pinyin_full": "lí",
    "components": [
        "言",
        "离"
    ],
    "xuan_note": "",
    "kai_note": "",
    "duan_notes": [
        {
            "explanation": "謧詍、",
            "note": "逗。"
        },
        {
            "explanation": "多言也。",
            "note": "玉篇云。欺謾之言。廣韵云。弄言。"
        },
        {
            "explanation": "从言。离聲。",
            "note": "呂之切。按廣韵之作支爲是。古音在十七部。"
        }
    ],
    "indexes": [
        "謧"
    ]
}