{
    "id": 1838,
    "wordhead": "鞅",
    "explanation": "頸靼也。从革央聲。",
    "volume": "03",
    "radical": "革",
    "pronunciation": "於兩切",
    "variants": [],
    "seal_character": "嘙",
    "pinyin": "yang",
    "pinyin_full": "yǎnɡ",
    "components": [
        "央",
        "革"
    ],
    "xuan_note": "",
    "kai_note": "",
    "duan_notes": [
        {
            "explanation": "頸靼也。",
            "note": "釋名。鞅、嬰也。喉下稱嬰。言嬰絡之也。按劉與許合。杜云在腹曰鞅。恐未然也。小雅鞅掌。毛曰。失容也。"
        },
        {
            "explanation": "从革。央聲。",
            "note": "於兩切。十部。"
        }
    ],
    "indexes": [
        "鞅"
    ]
}