{
    "id": 1968,
    "wordhead": "殺",
    "explanation": "戮也。从殳杀聲。凡殺之屬皆从殺。",
    "volume": "03",
    "radical": "殺",
    "pronunciation": "所八切",
    "variants": [
        {
            "wordhead": "𢿹",
            "explanation": "古文殺。",
            "seal_character": "囋"
        },
        {
            "wordhead": "𢽅",
            "explanation": "古文殺。",
            "seal_character": "囌"
        },
        {
            "wordhead": "𢁛",
            "explanation": "古文殺。",
            "seal_character": "囍"
        }
    ],
    "seal_character": "囊",
    "pinyin": "sha",
    "pinyin_full": "shā",
    "components": [
        "殳",
        "杀"
    ],
    "xuan_note": "臣鉉等曰：《說文》無杀字。相傳云音察。未知所出。",
    "kai_note": "",
    "duan_notes": [
        {
            "explanation": "戮也。",
            "note": "戈部曰。戮、殺也。"
        },
        {
            "explanation": "从殳。杀聲。",
            "note": "鉉等曰。說文無杀字。相傳音察。按張參曰。杀、古殺字。張說似近是。此如本作术、或加禾爲秫。所八切。十五部。"
        },
        {
            "explanation": "古文殺。",
            "note": "按鉉本宋刻無此字。李燾本同。"
        },
        {
            "explanation": "古文殺。",
            "note": "按此葢卽殺字轉寫譌變耳。加殳爲小篆之殺。此類甚多。古文四聲韵。𢁛爲崔希裕纂古。<>爲說文。則夏氏所據說文爲善本。正與張參說合。首字下當云從殳從杀。或譌爲杀聲也。"
        },
        {
            "explanation": "籒文殺。",
            "note": "按鉉本宋刻無此字。李燾本同。類篇云。史文殺作𠮁。臣光曰。說文失收。故集韵今不載。然則司馬公所據鉉本無𠮁信矣。今版本依鍇本增之耳。考工記閷字、不識何以從閃。今據殳部古文役、殺部籒文殺、殳皆作{(+凹-一)又[上下]}求之。知{(+凹-一)又[上下]}。譌爲閃。頓釋此疑。學者觸類而長之可也。"
        }
    ],
    "indexes": [
        "杀",
        "殺",
        "𢿹",
        "𢽅",
        "𢁛"
    ]
}