{
    "id": 2120,
    "wordhead": "眂",
    "explanation": "眂皃。从目氏聲。",
    "volume": "04",
    "radical": "目",
    "pronunciation": "承旨切",
    "variants": [],
    "seal_character": "坺",
    "pinyin": "shi",
    "pinyin_full": "shì",
    "components": [
        "氏",
        "目"
    ],
    "xuan_note": "",
    "kai_note": "",
    "duan_notes": [
        {
            "explanation": "視皃也。",
            "note": "馬融長笛賦。特麚昏髟。李曰昏、視也。髟、振髦也。按昏眂一字也。與眡別。眡、古文視。氐聲。在十五部。眂、氏聲。在十六部。宋元以來尟有知氏氐之不可通用者。"
        },
        {
            "explanation": "从目。氏聲。",
            "note": "承𣅀切。李善昌夷切。廣韵。眂眂、役目也。是支切。按古音在支紙韵。"
        }
    ],
    "indexes": [
        "眂"
    ]
}