{
    "id": 2270,
    "wordhead": "隹",
    "explanation": "鳥之短尾緫名也。象形。凡隹之屬皆从隹。",
    "volume": "04",
    "radical": "隹",
    "pronunciation": "職追切",
    "variants": [],
    "seal_character": "堜",
    "pinyin": "zhui",
    "pinyin_full": "zhuī",
    "components": [
        "隹"
    ],
    "xuan_note": "",
    "kai_note": "",
    "duan_notes": [
        {
            "explanation": "鳥之短尾緫名也。",
            "note": "短尾名隹。別於長尾名鳥。云緫名者、取數多也。亦鳥名。翩翩者鵻。夫不也。本又作隹。"
        },
        {
            "explanation": "象形。",
            "note": "職追切。十五部。"
        }
    ],
    "indexes": [
        "隹"
    ]
}