{
    "id": 2783,
    "wordhead": "釗",
    "explanation": "刓也。从刀从金。周康王名。",
    "volume": "04",
    "radical": "刀",
    "pronunciation": "止遙切",
    "variants": [],
    "seal_character": "婸",
    "pinyin": "zhao",
    "pinyin_full": "zhāo",
    "components": [
        "刀",
        "金"
    ],
    "xuan_note": "",
    "kai_note": "",
    "duan_notes": [
        {
            "explanation": "刓也。",
            "note": "未聞。"
        },
        {
            "explanation": "从刀金。",
            "note": "金有芒角。摩弄泯之。釋詁曰。釗、勉也。其引伸之義也。又曰。釗、見也。此假借釗爲昭也。孟子引書。昭我周王。郭引逸書。釗我周王。止遥切。二部。"
        }
    ],
    "indexes": [
        "钊",
        "釗"
    ]
}