{
    "id": 3061,
    "wordhead": "嚭",
    "explanation": "大也。从喜否聲。《春秋傳》：“吳有太宰嚭。”",
    "volume": "05",
    "radical": "喜",
    "pronunciation": "匹鄙切",
    "variants": [],
    "seal_character": "寀",
    "pinyin": "pi",
    "pinyin_full": "pǐ",
    "components": [
        "喜",
        "否"
    ],
    "xuan_note": "",
    "kai_note": "",
    "duan_notes": [
        {
            "explanation": "大也。从喜。否聲。",
            "note": "按訓大則當从丕。集韵一作噽是也。匹鄙切。十五部。"
        },
        {
            "explanation": "春秋傳吳有大宰嚭。",
            "note": "見左傳。"
        }
    ],
    "indexes": [
        "嚭"
    ]
}