{
    "id": 3386,
    "wordhead": "夂",
    "explanation": "从後至也。象人兩脛後有致之者。凡夂之屬皆从夂。讀若黹。",
    "volume": "05",
    "radical": "夂",
    "pronunciation": "陟侈切",
    "variants": [],
    "seal_character": "嵗",
    "pinyin": "zhi",
    "pinyin_full": "zhǐ",
    "components": [
        "夂"
    ],
    "xuan_note": "",
    "kai_note": "",
    "duan_notes": [
        {
            "explanation": "從後至也。",
            "note": "至當作致。"
        },
        {
            "explanation": "象人㒳脛後有致之者。",
            "note": "致、送詣也。"
        },
        {
            "explanation": "凡夂之屬皆从夂。讀若黹。",
            "note": "陟侈切。玉篇竹几切。十五部。"
        }
    ],
    "indexes": [
        "夂"
    ]
}