{
    "id": 3533,
    "wordhead": "机",
    "explanation": "木也。从木几聲。",
    "volume": "06",
    "radical": "木",
    "pronunciation": "居履切",
    "variants": [],
    "seal_character": "巵",
    "pinyin": "ji",
    "pinyin_full": "jī",
    "components": [
        "木",
        "几"
    ],
    "xuan_note": "",
    "kai_note": "",
    "duan_notes": [
        {
            "explanation": "机木也。",
            "note": "山海經。單狐之山多机木。族𥮐之山多松柏机桓。郭曰。机木似榆。可燒以糞稻田。音飢。按葢卽榿木也。今成都榿木樹。讀若豈平聲。楊雄蜀都賦曰。春机楊桺。机榿古今字。榿見杜詩。王安石詩以榿滋移爲韵。韵會音邱其切。與蜀語合。"
        },
        {
            "explanation": "從木。几聲。",
            "note": "居履切。十五部。"
        }
    ],
    "indexes": [
        "机"
    ]
}