{
    "id": 3753,
    "wordhead": "檄",
    "explanation": "二尺書。从木敫聲。",
    "volume": "06",
    "radical": "木",
    "pronunciation": "胡狄切",
    "variants": [],
    "seal_character": "廥",
    "pinyin": "xi",
    "pinyin_full": "xí",
    "components": [
        "木",
        "敫"
    ],
    "xuan_note": "",
    "kai_note": "",
    "duan_notes": [
        {
            "explanation": "尺二書。",
            "note": "各本作二尺書。小徐繫傳已佚。見韵會者作尺二書。葢古本也。李賢注光武紀曰。說文以木𥳑爲書。長尺二寸。謂之檄。以徵召也。與前書高紀注同。此葢出演說文。故語加詳。云尺二寸與鍇本合。但漢人多言尺一。未知其分別之詳。後漢書、水經注皆曰。李雲上書云。孔子言帝者、諦也。今尺一拜用。不經御省。是帝欲不諦乎。又後漢書儒林傳云。詔曰。乞楊生師。卽尺一出𦫵。文𨕖注引蕭子良古今篆𣜩文體曰。鶴頭書、偃波書俱詔板所用。在漢時則謂之尺一𥳑。獨𣃔曰。策書長二尺。以命諸侯王三公。三公以罪免。亦賜策。以尺一木。"
        },
        {
            "explanation": "從木。敫聲。",
            "note": "胡狄切。古音在二部。"
        }
    ],
    "indexes": [
        "檄"
    ]
}