{
    "id": 386,
    "wordhead": "薜",
    "explanation": "牡贊也。从艸辟聲。",
    "volume": "01",
    "radical": "艸",
    "pronunciation": "蒲計切",
    "variants": [],
    "seal_character": "侸",
    "pinyin": "bi",
    "pinyin_full": "bì",
    "components": [
        "辟",
        "艸"
    ],
    "xuan_note": "",
    "kai_note": "",
    "duan_notes": [
        {
            "explanation": "牡贊也。",
            "note": "見釋艸。"
        },
        {
            "explanation": "从艸。辟聲。",
            "note": "蒲計切。古音在十六部。"
        }
    ],
    "indexes": [
        "薜"
    ]
}