{
    "id": 3881,
    "wordhead": "束",
    "explanation": "縛也。从囗、木。凡束之屬皆从束。",
    "volume": "06",
    "radical": "束",
    "pronunciation": "書玉切",
    "variants": [],
    "seal_character": "彳",
    "pinyin": "shu",
    "pinyin_full": "shù",
    "components": [
        "木",
        "囗"
    ],
    "xuan_note": "",
    "kai_note": "",
    "duan_notes": [
        {
            "explanation": "縛也。",
            "note": "糸部曰。縛、束也。是爲轉注。襍記曰。納幣一束。束五兩。兩五尋。"
        }
    ],
    "indexes": [
        "束"
    ]
}