{
    "id": 3946,
    "wordhead": "賴",
    "explanation": "贏也。从貝剌聲。",
    "volume": "06",
    "radical": "貝",
    "pronunciation": "洛帶切",
    "variants": [],
    "seal_character": "徺",
    "pinyin": "lai",
    "pinyin_full": "lài",
    "components": [
        "剌",
        "貝"
    ],
    "xuan_note": "",
    "kai_note": "",
    "duan_notes": [
        {
            "explanation": "贏也。",
            "note": "高帝紀。始大人常㠯臣亡賴。應曰。賴者、恃也。晉曰。許愼云賴、利也。無利入於家也。或曰。江淮之閒謂小兒多詐狡獪爲亡賴。按今人云無賴者、謂其無衣食致然耳。方言云。賴、讎也。南楚之外曰賴。賴、取也。"
        },
        {
            "explanation": "从貝。剌聲。",
            "note": "洛帶切。十五部。"
        }
    ],
    "indexes": [
        "赖",
        "賴"
    ]
}