{
    "id": 4120,
    "wordhead": "郎",
    "explanation": "魯亭也。从邑良聲。",
    "volume": "06",
    "radical": "邑",
    "pronunciation": "魯當切",
    "variants": [],
    "seal_character": "恰",
    "pinyin": "lang",
    "pinyin_full": "lánɡ",
    "components": [
        "良",
        "邑"
    ],
    "xuan_note": "",
    "kai_note": "",
    "duan_notes": [
        {
            "explanation": "魯亭也。",
            "note": "春秋隱元年。費伯率師城郎。桓四年。公狩于郎。十年。齊矦衞矦鄭伯來戰于郎。莊八年。師次于郎。以俟陳人蔡人。三十一年。築臺于郎。哀十一年。戰于郊。檀弓作戰於郎。鄭曰。郎、魯近邑也。杜云。郎、魯邑。高平方與縣東南有郁郎亭。按以郎爲男子之偁及官名者、皆良之假借字也。"
        },
        {
            "explanation": "从邑。良聲。",
            "note": "魯當切。十部。"
        }
    ],
    "indexes": [
        "郎"
    ]
}