{
    "id": 4196,
    "wordhead": "暉",
    "explanation": "光也。从日軍聲。",
    "volume": "07",
    "radical": "日",
    "pronunciation": "許歸切",
    "variants": [],
    "seal_character": "悿",
    "pinyin": "hui",
    "pinyin_full": "huī",
    "components": [
        "軍",
        "日"
    ],
    "xuan_note": "",
    "kai_note": "",
    "duan_notes": [
        {
            "explanation": "灮也。",
            "note": "按光也二字當作日光氣也四字。篆體暉當作暈。周禮暈作煇。古文叚借字。眡𥛆掌十煇之法。以觀妖祥。辨吉凶。一曰𥛆。二曰象。三曰鑴。四曰監。五曰闇。六曰瞢。七曰彌。八曰敘。九曰隮。十曰想。鄭司農云。煇謂日光炁也。按日光氣謂日光捲結之氣。釋名曰。暈、捲也。氣在外捲結之也。日月皆然。孟康曰。暈、日旁氣也。篆體日在上。或移之在旁。此篆遂改爲暉。改其訓曰光。與火部之煇不別。葢淺者爲之。乃致鉉以暈爲新附篆矣。"
        },
        {
            "explanation": "从日。軍聲。",
            "note": "軍者、圜圍也。此以形聲包會意。王問切。十三部。大徐許歸切。非。"
        }
    ],
    "indexes": [
        "晖",
        "暉"
    ]
}