{
    "id": 4225,
    "wordhead": "㬮",
    "explanation": "安㬮，温也。从日難聲。",
    "volume": "07",
    "radical": "日",
    "pronunciation": "奴案切",
    "variants": [],
    "seal_character": "惝",
    "pinyin": "nan",
    "pinyin_full": "nàn",
    "components": [
        "難",
        "日"
    ],
    "xuan_note": "",
    "kai_note": "",
    "duan_notes": [
        {
            "explanation": "安㬮、",
            "note": "逗。疊韵字也。"
        },
        {
            "explanation": "𥁕也。",
            "note": "𥁕各本作溫。今正。說詳水部。安㬮猶溫存也。二字皆平聲。廣雅云。暍、㬮、暖也。安作暍語之轉耳。巾部云。讀若水溫㬮。則安亦作溫。"
        },
        {
            "explanation": "从日。難聲。",
            "note": "奴案切。十四部。按廣韵、集韵、類篇㬮皆讀平聲。入山韵。玉篇㬮亦奴達切。平則二字皆平。去則二字皆去。入則二字皆入是之謂疊韵。"
        }
    ],
    "indexes": [
        "㬮"
    ]
}