{
    "id": 4327,
    "wordhead": "甬",
    "explanation": "艸木華甬甬然也。从𢎘用聲。",
    "volume": "07",
    "radical": "𢎘",
    "pronunciation": "余隴切",
    "variants": [],
    "seal_character": "慚",
    "pinyin": "yong",
    "pinyin_full": "yǒnɡ",
    "components": [
        "用"
    ],
    "xuan_note": "",
    "kai_note": "",
    "duan_notes": [
        {
            "explanation": "艸木𠌶甬甬然也。",
            "note": "小徐曰。甬之言湧也。若水湧出也。周禮。鐘柄爲甬。按凡从甬聲之字皆興起之意。"
        },
        {
            "explanation": "从㔾(𢎘)。用聲。",
            "note": "餘隴切。十部。"
        }
    ],
    "indexes": [
        "甬"
    ]
}