{
    "id": 4413,
    "wordhead": "稾",
    "explanation": "稈也。从禾高聲。",
    "volume": "07",
    "radical": "禾",
    "pronunciation": "古老切",
    "variants": [],
    "seal_character": "懀",
    "pinyin": "gao",
    "pinyin_full": "ɡǎo",
    "components": [
        "禾",
        "高"
    ],
    "xuan_note": "",
    "kai_note": "",
    "duan_notes": [
        {
            "explanation": "稈也。",
            "note": "廣雅、左傳注皆云。秆、稾也。叚借爲矢榦之稾、屈平屬艸稾之稾。"
        },
        {
            "explanation": "从禾。高聲。",
            "note": "古老切。二部。"
        }
    ],
    "indexes": [
        "稾"
    ]
}