{
    "id": 4875,
    "wordhead": "幠",
    "explanation": "覆也。从巾無聲。",
    "volume": "07",
    "radical": "巾",
    "pronunciation": "荒烏切",
    "variants": [],
    "seal_character": "插",
    "pinyin": "hu",
    "pinyin_full": "hū",
    "components": [
        "無",
        "巾"
    ],
    "xuan_note": "",
    "kai_note": "",
    "duan_notes": [
        {
            "explanation": "覆也。",
            "note": "喪大記。幠用斂衾。釋詁。幠、大也。幠、有也。皆覆義之引伸也。投壷曰。無幠無敖。注曰。幠、敖皆慢也。又其引伸也。斯干以芋爲幠。"
        },
        {
            "explanation": "从巾。𣞤聲。",
            "note": "荒鳥切。五部。"
        }
    ],
    "indexes": [
        "幠"
    ]
}