{
    "id": 5334,
    "wordhead": "裺",
    "explanation": "褗謂之裺。从衣奄聲。",
    "volume": "08",
    "radical": "衣",
    "pronunciation": "依檢切",
    "variants": [],
    "seal_character": "旃",
    "pinyin": "yan",
    "pinyin_full": "yǎn",
    "components": [
        "衣",
        "奄"
    ],
    "xuan_note": "",
    "kai_note": "",
    "duan_notes": [
        {
            "explanation": "褗謂之裺。",
            "note": "葢奄覆之義。方言曰。裺謂之襦。又曰。懸裺謂之緣。又曰。繞循謂之？裺。皆不與許同。"
        },
        {
            "explanation": "从衣。𡘹聲。",
            "note": "依檢切。八部。"
        }
    ],
    "indexes": [
        "裺"
    ]
}