{
    "id": 5444,
    "wordhead": "先",
    "explanation": "前進也。从儿从之。凡先之屬皆从先。",
    "volume": "08",
    "radical": "先",
    "pronunciation": "穌前切",
    "variants": [],
    "seal_character": "晁",
    "pinyin": "xian",
    "pinyin_full": "xiān",
    "components": [
        "人",
        "之"
    ],
    "xuan_note": "臣鉉等曰：之人上，是先也。",
    "kai_note": "",
    "duan_notes": [
        {
            "explanation": "前進也。",
            "note": "前當作歬。不行而進曰歬。凡言歬者緩詞。凡言先者急詞也。其爲進一也。"
        },
        {
            "explanation": "从儿之。",
            "note": "之者、出也。引伸爲往也。蘇前切。古音在十三部。讀若先聲之詵。"
        }
    ],
    "indexes": [
        "先"
    ]
}