{
    "id": 5787,
    "wordhead": "胞",
    "explanation": "兒生裹也。从肉从包。",
    "volume": "09",
    "radical": "包",
    "pronunciation": "匹交切",
    "variants": [],
    "seal_character": "枽",
    "pinyin": "pao",
    "pinyin_full": "bāo",
    "components": [
        "肉",
        "包"
    ],
    "xuan_note": "",
    "kai_note": "",
    "duan_notes": [
        {
            "explanation": "兒生裹也。",
            "note": "包謂母腹。胞謂胎衣。小雅。不屬于毛。不離于裏。箋云。今我獨不得父皮膚之氣乎。獨不處母之胞胎乎。釋文胞音包。今俗語同胞是也。其借爲脬字、則讀匹交切。脬者、旁光也。腹中水府也。"
        },
        {
            "explanation": "从肉包。",
            "note": "包子之肉也。不入肉部者、重包也。包亦聲。匹交切。古音在三部。"
        }
    ],
    "indexes": [
        "胞"
    ]
}