{
    "id": 6002,
    "wordhead": "磿",
    "explanation": "石聲也。从石厤聲。",
    "volume": "09",
    "radical": "石",
    "pronunciation": "郎擊切",
    "variants": [],
    "seal_character": "梪",
    "pinyin": "li",
    "pinyin_full": "lì",
    "components": [
        "石",
        "厤"
    ],
    "xuan_note": "",
    "kai_note": "",
    "duan_notes": [
        {
            "explanation": "石聲也。",
            "note": "左思蜀都賦原稾。鬼單飛丸以䃒礰。集韵曰。礰卽磿字。磿爲石聲者、謂其聲歷歷然。玉篇曰。石小聲是也。周禮遂師。抱磿。後鄭云。磿者、適歷執紼者名也。是叚磿爲歷。史記樂毅傳。故鼎反乎磿室。戰國策作歷室。○蜀都賦語見太平御覽。世說新語注引左思別傳作鬼彈飛丸以礌礉。按鬼彈見水經注若水篇。非佳物也。故改定之本無此語。"
        },
        {
            "explanation": "从石厤聲。",
            "note": "郎擊切。十六部。"
        }
    ],
    "indexes": [
        "磿"
    ]
}