{
    "id": 618,
    "wordhead": "䒼",
    "explanation": "蠶薄也。从艸曲聲。",
    "volume": "01",
    "radical": "艸",
    "pronunciation": "丘玉切",
    "variants": [],
    "seal_character": "傱",
    "pinyin": "qu",
    "pinyin_full": "qū",
    "components": [
        "艸",
        "曲"
    ],
    "xuan_note": "",
    "kai_note": "",
    "duan_notes": [
        {
            "explanation": "蠶薄也。",
            "note": "幽風毛傳曰。豫畜萑葦。可以爲曲也。月令。季春、具曲植筥筐。注曰。曲、薄也。方言。薄、宋魏陳楚江淮之閒謂之䒼。或謂之麴。自關而西謂之薄。南楚謂之蓬薄。案曲與䒼同。曲部云。或說曲、蠶薄也。是許兼用此二形。"
        },
        {
            "explanation": "从艸。𠚖聲。",
            "note": "邱玉切。三部。"
        }
    ],
    "indexes": [
        "䒼"
    ]
}