{
    "id": 6367,
    "wordhead": "鼨",
    "explanation": "豹文鼠也。从鼠冬聲。",
    "volume": "10",
    "radical": "鼠",
    "pronunciation": "職戎切",
    "variants": [
        {
            "wordhead": "𪕄",
            "explanation": "籒文省。",
            "seal_character": "橃"
        }
    ],
    "seal_character": "橂",
    "pinyin": "zhong",
    "pinyin_full": "zhōnɡ",
    "components": [
        "冬",
        "鼠"
    ],
    "xuan_note": "",
    "kai_note": "",
    "duan_notes": [
        {
            "explanation": "豹文鼠也。",
            "note": "釋獸曰。鼨鼠豹文鼮鼠。郭讀以豹文下屬。云鼠文采如豹者。漢武帝時得此鼠。孝廉郞終軍知之。賜絹百匹。按文𨕖注、藝文類聚皆引竇氏家傳載此事。系之光武時竇攸。以豹文爲鼮鼠則同。惟唐書盧若虚傳云。時有𫉬異鼠者。豹首虎臆。大如拳。職方辛怡諫謂之鼮鼠而賦之。若虚曰。非也。此許愼所謂鼨鼠。豹文而形小。一坐盡驚。玉裁謂。他人讀爾雅皆豹文鼮鼠爲句。終軍、竇攸、辛怡諫從之。許讀爾雅鼨鼠豹文爲句。盧若虚從之。其是非訖難定也。許有鼨無鼮。疑爾雅六字爲一物。"
        },
        {
            "explanation": "从鼠。冬聲。",
            "note": "職戎切。九部。"
        },
        {
            "explanation": "籒文省。",
            "note": "𠔾古文終。"
        }
    ],
    "indexes": [
        "鼨",
        "𪕄"
    ]
}