{
    "id": 6676,
    "wordhead": "恉",
    "explanation": "意也。从心旨聲。",
    "volume": "10",
    "radical": "心",
    "pronunciation": "職雉切",
    "variants": [],
    "seal_character": "殟",
    "pinyin": "zhi",
    "pinyin_full": "zhǐ",
    "components": [
        "心",
        "旨"
    ],
    "xuan_note": "",
    "kai_note": "",
    "duan_notes": [
        {
            "explanation": "意也。",
            "note": "今字或作旨、或作指。皆非本字也。許序曰。曉學者達神恉。"
        },
        {
            "explanation": "从心。旨聲。",
            "note": "職雉切。十五部。"
        }
    ],
    "indexes": [
        "恉"
    ]
}