{
    "id": 7020,
    "wordhead": "溳",
    "explanation": "水。出南陽蔡陽，東入夏水。从水員聲。",
    "volume": "11",
    "radical": "水",
    "pronunciation": "王分切",
    "variants": [],
    "seal_character": "洑",
    "pinyin": "yun",
    "pinyin_full": "yún",
    "components": [
        "水",
        "員"
    ],
    "xuan_note": "",
    "kai_note": "",
    "duan_notes": [
        {
            "explanation": "溳水。出南陽蔡陽。東入夏水。",
            "note": "南陽郡蔡陽、二志同。故城當在今湖北德安府隨州境內。夏水見上文沔字下。水經曰。溳水、出蔡陽縣。東南過隨縣西。又南過江夏安陸縣西。又東南入於夏。酈云。溳水、出縣東南大洪山。山在隨郡之西南。竟陵之東北。槃基所跨、廣員百餘里。今溳水出大洪山之陰。東南經隨州應山縣、安陸縣、雲夢縣、應城縣。至漢川縣溳口塘入漢。源流長五百里。入漢、卽古之入夏水也。今漢夏不分。"
        },
        {
            "explanation": "从水。員聲。",
            "note": "王分切。十三部。按水徑德安府治、卽古鄖國也。鄖葢以水得名。水經注曰。隨水至安陸縣故城西入於溳。故鄖城也。左傳定四年。吳敗楚於柏舉。及於淸發。葢溳水兼淸水之目矣。"
        }
    ],
    "indexes": [
        "溳"
    ]
}