{
    "id": 7165,
    "wordhead": "清",
    "explanation": "朖也。澂水之皃。从水青聲。",
    "volume": "11",
    "radical": "水",
    "pronunciation": "七情切",
    "variants": [],
    "seal_character": "涤",
    "pinyin": "qing",
    "pinyin_full": "qīnɡ",
    "components": [
        "青",
        "水"
    ],
    "xuan_note": "",
    "kai_note": "",
    "duan_notes": [
        {
            "explanation": "朖也。澂水之皃。",
            "note": "朖者、明也。澂而後明。故云澂水之皃。引伸之、凡潔曰淸。凡人潔之亦曰淸。同瀞。"
        },
        {
            "explanation": "从水。靑聲。",
            "note": "七情切。十一部。"
        }
    ],
    "indexes": [
        "清"
    ]
}