{
    "id": 7310,
    "wordhead": "洿",
    "explanation": "濁水不流也。一曰窳下也。从水夸聲。",
    "volume": "11",
    "radical": "水",
    "pronunciation": "哀都切",
    "variants": [],
    "seal_character": "湂",
    "pinyin": "wu",
    "pinyin_full": "wū",
    "components": [
        "水",
        "夸"
    ],
    "xuan_note": "",
    "kai_note": "",
    "duan_notes": [
        {
            "explanation": "濁水不流也。",
            "note": "服虔注左傳云。水不流謂之汙。按汙卽洿之假借字。孟子梁惠王作洿。滕文公用汙。玄應引說文濁水不流池也。引字林濁水不流曰洿。宜有池爲長。"
        },
        {
            "explanation": "一曰窊下也。",
            "note": "窊本作窳。今改。"
        },
        {
            "explanation": "从水。夸聲。",
            "note": "哀都切。五部。"
        }
    ],
    "indexes": [
        "洿"
    ]
}