{
    "id": 7343,
    "wordhead": "澱",
    "explanation": "滓滋也。从水殿聲。",
    "volume": "11",
    "radical": "水",
    "pronunciation": "堂練切",
    "variants": [],
    "seal_character": "湥",
    "pinyin": "dian",
    "pinyin_full": "diàn",
    "components": [
        "水",
        "殿"
    ],
    "xuan_note": "",
    "kai_note": "",
    "duan_notes": [
        {
            "explanation": "滓垽也。",
            "note": "釋器曰。澱謂之垽。土部曰。垽、澱也。黑部曰。？謂之垽。按𪑩與澱異字而音義同。實則一字也。"
        },
        {
            "explanation": "从水。𣪍聲。",
            "note": "堂練切。十三部。"
        }
    ],
    "indexes": [
        "淀",
        "澱"
    ]
}