{
    "id": 7443,
    "wordhead": "川",
    "explanation": "貫穿通流水也。《虞書》曰：“濬く巜，距川。”言深く巜之水會爲川也。凡川之屬皆从川。",
    "volume": "11",
    "radical": "川",
    "pronunciation": "昌緣切",
    "variants": [],
    "seal_character": "滑",
    "pinyin": "chuan",
    "pinyin_full": "chuān",
    "components": [
        "川"
    ],
    "xuan_note": "",
    "kai_note": "",
    "duan_notes": [
        {
            "explanation": "毌穿通流水也。",
            "note": "毌各本作貫。毌、穿物持之也。穿、通也。巛則毌穿通流。又大於巜矣。水有始出謂川者。如爾雅水注川曰谿、許云泉出通川爲谷是也。有絕大乃謂川者。如皋陶謨𡿨巜距川、攷工記澮達於川是也。本小水之名、因以爲大水之名。"
        },
        {
            "explanation": "虞書曰。",
            "note": "謂古文皋陶謨。"
        },
        {
            "explanation": "濬𡿨巜歫巛。",
            "note": "歫各本作距。今正。今尙書作畎澮距川者、後人所改也。"
        },
        {
            "explanation": "言深𡿨巜之水會爲川也。",
            "note": "此偁尙書釋之。以見尙書之川與川字有間矣。川今昌緣切。古音在十三部。讀如春。雲漢之詩是也。"
        }
    ],
    "indexes": [
        "川"
    ]
}