{
    "id": 7544,
    "wordhead": "𩹾",
    "explanation": "魚。似鼈，無甲，有尾，無足，口在腹下。从魚納聲。",
    "volume": "11",
    "radical": "魚",
    "pronunciation": "奴荅切",
    "variants": [],
    "seal_character": "潒",
    "pinyin": "na",
    "pinyin_full": "nà",
    "components": [
        "魚",
        "納"
    ],
    "xuan_note": "",
    "kai_note": "",
    "duan_notes": [
        {
            "explanation": "𩹾魚。佀鼈無甲。有尾無足。口在腹下。从魚。納聲。",
            "note": "按此篆玉篇作𩹾。廣韵作魶。史記上林賦有魶字。云魶一作鰨。奴荅切。八部。"
        }
    ],
    "indexes": [
        "𩹾"
    ]
}