{
    "id": 7550,
    "wordhead": "鮪",
    "explanation": "鮥也。《周禮》：“春獻王鮪。”从魚有聲。",
    "volume": "11",
    "radical": "魚",
    "pronunciation": "榮美切",
    "variants": [],
    "seal_character": "潘",
    "pinyin": "wei",
    "pinyin_full": "wěi",
    "components": [
        "有",
        "魚"
    ],
    "xuan_note": "",
    "kai_note": "",
    "duan_notes": [
        {
            "explanation": "鮥也。",
            "note": "毛詩衞風傳曰。鮪、鮥也。許本之。陸璣疏曰。鮪魚形似鱣而靑黑。頭小而尖。似鐵兜鍪。口亦在頷下。其甲可以摩薑。大者不過七八尺。益州人謂之䱍䲛。大者爲王鮪。小者爲鮛鮪。一名鮥。肉色白。味不如鱣也。郭氏山海經傳曰。鮪卽鱏也。似鱣而長鼻。體無鱗甲。按卽今之鱘魚也。"
        },
        {
            "explanation": "周禮。春獻王鮪。",
            "note": "天官䱷人文。注曰。王鮪、鮪之大者。引月令季春薦鮪于寢廟。西京賦曰。王鮪岫居。薛綜、陸璣、李奇、酈道元皆言鮪自南方江中來。至河南鞏穴又入河。度龍門。葢古事如此。不然。鮪出江中。何以西周能薦鮪也。"
        },
        {
            "explanation": "从魚。有聲。",
            "note": "榮美切。古音在一部。讀如以。"
        }
    ],
    "indexes": [
        "鲔",
        "鮪"
    ]
}