{
    "id": 768,
    "wordhead": "犀",
    "explanation": "南徼外牛。一角在鼻，一角在頂，似豕。从牛㞑聲。",
    "volume": "02",
    "radical": "牛",
    "pronunciation": "先稽切",
    "variants": [],
    "seal_character": "兕",
    "pinyin": "xi",
    "pinyin_full": "xī",
    "components": [
        "牛",
        "尾"
    ],
    "xuan_note": "",
    "kai_note": "",
    "duan_notes": [
        {
            "explanation": "徼外牛。",
            "note": "各本有南字。今依韵會。楚語曰。巴浦之犀犛兕象。其可盡乎。後漢章帝紀。蠻夷獻生犀、白雉。"
        },
        {
            "explanation": "一角在鼻。一角在頂。",
            "note": "爾雅山海經郭注、劉欣期交州記皆云有三角。一在頂上。一在頟上。一在鼻上。鼻上角短小。按晉語。角犀豐盈。孟子注。頟角犀厥地。戰國策。眉目準頞權衡。犀角偃月。此皆謂人自鼻至頂豐滿。如相書所云伏犀貫頂也。"
        },
        {
            "explanation": "佀豕。",
            "note": "見釋獸。劉欣期云。其毛如豕。頭如馬。郭璞云。形似水牛。豬頭。說各不同也。"
        },
        {
            "explanation": "从牛。尾聲。",
            "note": "先稽切。十五部。"
        }
    ],
    "indexes": [
        "犀"
    ]
}