{
    "id": 7860,
    "wordhead": "捉",
    "explanation": "搤也。从手足聲。一曰握也。",
    "volume": "12",
    "radical": "手",
    "pronunciation": "側角切",
    "variants": [],
    "seal_character": "炰",
    "pinyin": "zhuo",
    "pinyin_full": "zhuō",
    "components": [
        "手",
        "足"
    ],
    "xuan_note": "",
    "kai_note": "",
    "duan_notes": [
        {
            "explanation": "搤也。从手。足聲。",
            "note": "側角切。三部。"
        },
        {
            "explanation": "一曰握也。",
            "note": "上文云握者、搤持也。與此爲轉注。"
        }
    ],
    "indexes": [
        "捉"
    ]
}