{
    "id": 8294,
    "wordhead": "㜮",
    "explanation": "過差也。从女監聲。《論語》曰：“小人窮斯㜮矣。”",
    "volume": "12",
    "radical": "女",
    "pronunciation": "盧瞰切",
    "variants": [],
    "seal_character": "牸",
    "pinyin": "lan",
    "pinyin_full": "làn",
    "components": [
        "女",
        "監"
    ],
    "xuan_note": "",
    "kai_note": "",
    "duan_notes": [
        {
            "explanation": "過差也。",
            "note": "差忒者、不相值也。凡不得其當曰過差。亦曰㜮。今字多以濫爲之。商頌。不僭不濫。傳曰。賞不僭、㓝不濫也。左氏曰。賞僭則懼及淫人。㓝濫則懼及善人。其字皆可作㜮。濫行而㜮廢矣。"
        },
        {
            "explanation": "从女。監聲。",
            "note": "盧噉切。八部。"
        },
        {
            "explanation": "論語曰。小人竆斯㜮矣。",
            "note": "衞靈公篇文。今作濫。"
        }
    ],
    "indexes": [
        "㜮"
    ]
}