{
    "id": 8436,
    "wordhead": "弓",
    "explanation": "以近窮遠。象形。古者揮作弓。《周禮》六弓：王弓、弧弓以射甲革甚質；夾弓、庾弓以射干矦鳥獸；唐弓、大弓以授學射者。凡弓之屬皆从弓。",
    "volume": "12",
    "radical": "弓",
    "pronunciation": "居戎切",
    "variants": [],
    "seal_character": "猜",
    "pinyin": "gong",
    "pinyin_full": "ɡōnɡ",
    "components": [
        "弓"
    ],
    "xuan_note": "",
    "kai_note": "",
    "duan_notes": [
        {
            "explanation": "竆也。",
            "note": "補此二字。以㬪韵爲訓之例也。"
        },
        {
            "explanation": "㠯近竆遠者。",
            "note": "者字今補。"
        },
        {
            "explanation": "象形。",
            "note": "居戎切。古音在六部。讀如肱。"
        },
        {
            "explanation": "古者揮作弓。",
            "note": "郭景純引世本曰。牟夷作矢。揮作弓。此等皆當出世本作篇。揮、黃帝臣。"
        },
        {
            "explanation": "周禮。六弓。王弓、弧弓㠯䠶甲革甚質。夾弓、庾弓㠯䠶干侯鳥獸。唐弓、大弓㠯授學䠶者。",
            "note": "夏官司弓矢文也。說詳鄭注。甚質今作椹質。按故書作鞎。大鄭云。鞎當爲椹。許書無椹字。葢許從鄭。鄭本作甚也。干今作豻。"
        }
    ],
    "indexes": [
        "弓"
    ]
}