{
    "id": 8483,
    "wordhead": "紇",
    "explanation": "絲下也。从糸气聲。《春秋傳》有臧孫紇。",
    "volume": "13",
    "radical": "糸",
    "pronunciation": "下沒切",
    "variants": [],
    "seal_character": "獕",
    "pinyin": "he",
    "pinyin_full": "hé",
    "components": [
        "气",
        "糸"
    ],
    "xuan_note": "",
    "kai_note": "",
    "duan_notes": [
        {
            "explanation": "絲下也。",
            "note": "謂絲之下、者也。"
        },
        {
            "explanation": "从糸。气聲。",
            "note": "下𣳚切。十五部。"
        }
    ],
    "indexes": [
        "纥",
        "紇"
    ]
}