{
    "id": 8487,
    "wordhead": "繀",
    "explanation": "著絲於筟車也。从糸崔聲。",
    "volume": "13",
    "radical": "糸",
    "pronunciation": "穌對切",
    "variants": [],
    "seal_character": "獙",
    "pinyin": "sui",
    "pinyin_full": "suì",
    "components": [
        "崔",
        "糸"
    ],
    "xuan_note": "",
    "kai_note": "",
    "duan_notes": [
        {
            "explanation": "箸絲於筟車也。",
            "note": "竹部曰。筟、筳也。筳、繀絲筦也。筟車亦曰繀車。方言曰。繀車、趙魏之閒謂之轣轆。車齊海岱之閒謂之道軌。箸絲於筳謂之繀。"
        },
        {
            "explanation": "从糸。崔聲。",
            "note": "穌對切。十五部。"
        }
    ],
    "indexes": [
        "繀"
    ]
}