{
    "id": 9069,
    "wordhead": "壙",
    "explanation": "塹穴也。一曰大也。从土廣聲。",
    "volume": "13",
    "radical": "土",
    "pronunciation": "苦謗切",
    "variants": [],
    "seal_character": "痾",
    "pinyin": "kuang",
    "pinyin_full": "kuànɡ",
    "components": [
        "土",
        "廣"
    ],
    "xuan_note": "",
    "kai_note": "",
    "duan_notes": [
        {
            "explanation": "塹穴也。",
            "note": "謂塹地爲穴也。墓穴也。周禮方相氏。及墓入壙。以戈擊四隅。鄭曰。壙、穿地中也。"
        },
        {
            "explanation": "从土。廣聲。",
            "note": "苦謗切。十部。"
        },
        {
            "explanation": "一曰大也。",
            "note": "孟子曰。水之就下。獸之走壙。"
        }
    ],
    "indexes": [
        "圹",
        "壙"
    ]
}