{
    "id": 9256,
    "wordhead": "銼",
    "explanation": "鍑也。从金坐聲。",
    "volume": "14",
    "radical": "金",
    "pronunciation": "昨禾切",
    "variants": [],
    "seal_character": "盒",
    "pinyin": "cuo",
    "pinyin_full": "cuò",
    "components": [
        "金",
        "坐"
    ],
    "xuan_note": "",
    "kai_note": "",
    "duan_notes": [
        {
            "explanation": "銼𨰠。",
            "note": "二字依全書通例補。曡韵字。"
        },
        {
            "explanation": "鍑也。从金。𡋲聲。",
            "note": "昨禾切。十七部。"
        }
    ],
    "indexes": [
        "锉",
        "銼"
    ]
}