{
    "id": 9371,
    "wordhead": "銴",
    "explanation": "車樘結也。一曰銅生五色也。从金折聲。讀若誓。",
    "volume": "14",
    "radical": "金",
    "pronunciation": "時制切",
    "variants": [],
    "seal_character": "睎",
    "pinyin": "shi",
    "pinyin_full": "shì",
    "components": [
        "金",
        "折"
    ],
    "xuan_note": "",
    "kai_note": "",
    "duan_notes": [
        {
            "explanation": "車樘結也。",
            "note": "木部曰。樘、衺柱也。古音堂。今音丑庚切。考工記注曰。䟫讀如牚距之牚、車牚之牚。然則車樘、漢人語也。急就篇、釋名作棠。劉𤋮曰。棠、？也。在車㒳旁。？？使不得進卻也。今按其結曰銴。其制未詳。葢可以系車？者。"
        },
        {
            "explanation": "从金。㪿聲。讀若誓。",
            "note": "時制切。十五部。"
        },
        {
            "explanation": "一曰銅生五色也。",
            "note": "如古銅器朱翠之色。"
        }
    ],
    "indexes": [
        "銴"
    ]
}