{
    "id": 9486,
    "wordhead": "轛",
    "explanation": "車橫軨也。从車對聲。《周禮》曰：“參分軹圍，去一以爲轛圍。”",
    "volume": "14",
    "radical": "車",
    "pronunciation": "追萃切",
    "variants": [],
    "seal_character": "矈",
    "pinyin": "zhui",
    "pinyin_full": "zhuì",
    "components": [
        "車",
        "對"
    ],
    "xuan_note": "",
    "kai_note": "",
    "duan_notes": [
        {
            "explanation": "車橫軨也。",
            "note": "謂車闌也。木部橫下曰。闌木也。攷工記曰。參分軹圍、去一以爲轛圍。注。兵車之轛圍、二寸八十一分寸之十四。轛、式之植者橫者也。鄭司農云。謂車輿軨立者也。按許云橫軨也。橫訓闌。則直者衡者皆在內矣。漢人從衡字衹作衡。不作橫。橫者、桄也。後鄭又云。轛者、以其鄉人爲名。按字所以从對與。"
        },
        {
            "explanation": "从車。𡭊聲。",
            "note": "追萃切。十五部、廣韵作轛。都隊切。"
        },
        {
            "explanation": "周禮曰。參分軹圍。去一㠯爲轛圍。",
            "note": "輿人職文。按鄭云輢之植者衡者也。與轂末同名。許君軹下云。車輪小穿。不言别義。而此引參分軹圍之文。令學者疑。葢其疏也。"
        }
    ],
    "indexes": [
        "轛"
    ]
}