{
    "id": 9552,
    "wordhead": "轒",
    "explanation": "淮陽名車穹隆轒。从車賁聲。",
    "volume": "14",
    "radical": "車",
    "pronunciation": "符分切",
    "variants": [],
    "seal_character": "砑",
    "pinyin": "fen",
    "pinyin_full": "fén",
    "components": [
        "車",
        "賁"
    ],
    "xuan_note": "",
    "kai_note": "",
    "duan_notes": [
        {
            "explanation": "淮陽名車穹隆轒。",
            "note": "淮陽、漢國。有縣九。今開封府陳州以南是其地。車穹隆、卽車葢弓也。方言曰。車枸簍、宋魏陳楚之閒謂之䈐。或謂之𥳎籠。秦晉之閒自關而西謂之枸簍。西隴謂之？。南楚之外謂之篷。或謂之隆屈。郭云。卽車弓也。按許之穹隆卽𥳎籠也。許之轒葢卽㮥字與。抑淮陽謂之轒、爲方言所不載也。釋名曰隆强。或曰車弓。長楊賦碎轒輼。别一義也。"
        },
        {
            "explanation": "从車。賁聲。",
            "note": "符分切。十三部。按此篆當與上轑葢弓也爲伍。轑言其分。轒言其合也。廁此者、後人亂之。"
        }
    ],
    "indexes": [
        "轒"
    ]
}