{
    "id": 9620,
    "wordhead": "隱",
    "explanation": "蔽也。从𨸏㥯聲。",
    "volume": "14",
    "radical": "𨸏",
    "pronunciation": "於謹切",
    "variants": [],
    "seal_character": "硛",
    "pinyin": "yin",
    "pinyin_full": "yǐn",
    "components": [
        "阜"
    ],
    "xuan_note": "",
    "kai_note": "",
    "duan_notes": [
        {
            "explanation": "蔽也。",
            "note": "艸部曰。蔽茀、小皃也。小則不可見。故隱之訓曰蔽。若孟子隱几字則當爲？。𠬪部曰。？、有所據也。"
        },
        {
            "explanation": "从𨸏。㥯聲。",
            "note": "於謹切。十三部。"
        }
    ],
    "indexes": [
        "隐",
        "隱"
    ]
}