{
    "id": 9642,
    "wordhead": "阽",
    "explanation": "壁危也。从𨸏占聲。",
    "volume": "14",
    "radical": "𨸏",
    "pronunciation": "余廉切",
    "variants": [],
    "seal_character": "硲",
    "pinyin": "yan",
    "pinyin_full": "yán",
    "components": [
        "占",
        "阜"
    ],
    "xuan_note": "",
    "kai_note": "",
    "duan_notes": [
        {
            "explanation": "壁危也。",
            "note": "引申爲凡物之危。漢文帝詔曰。或阽於死亡。如淳曰。阽、近邊欲墮之意。"
        },
        {
            "explanation": "从𨸏。",
            "note": "壁高故从𨸏。"
        },
        {
            "explanation": "占聲。",
            "note": "余廉切。古音在七部。服虔音反坫之坫。孟康音屋檐之檐。"
        }
    ],
    "indexes": [
        "阽"
    ]
}