{
    "id": 974,
    "wordhead": "單",
    "explanation": "大也。从吅、红，吅亦聲。闕。",
    "volume": "02",
    "radical": "吅",
    "pronunciation": "都寒切",
    "variants": [],
    "seal_character": "刻",
    "pinyin": "dan",
    "pinyin_full": "dān",
    "components": [
        "吅"
    ],
    "xuan_note": "",
    "kai_note": "",
    "duan_notes": [
        {
            "explanation": "大也。",
            "note": "當爲大言也。淺人刪言字。如誣加言也。淺人亦刪言字。爾雅、廣雅說大皆無單。引伸爲雙之反對。大雅。其軍三單。毛云。三單、相襲也。鄭云。丁夫適滿三軍之數。無羨卒也。"
        },
        {
            "explanation": "从吅？。",
            "note": "大言故从吅。"
        },
        {
            "explanation": "吅亦聲。",
            "note": "都寒切。十四部。"
        },
        {
            "explanation": "闕。",
            "note": "當云？闕。謂？形未聞也。"
        }
    ],
    "indexes": [
        "单",
        "單"
    ]
}